{
    "spotlightVideos": [
        {
            "id": 1,
            "screen": "home",
            "videoId": 1
        },
        {
            "id": 2,
            "screen": "news",
            "videoId": 13
        }
    ],
    "videos": [
        {
            "id": 1,
            "title": "Por que aprender Libras?",
            "url": "https://www.youtube.com/embed/vw4stB2__R4",
            "description": "Aprenda com o Marcos os 5 motivos para você aprender Libras",
            "playlistId": 4
        },
        {
            "id": 2,
            "title": "MÚSICA",
            "url": "https://www.youtube.com/embed/eGDkz44wHRk",
            "description": "Meu Abrigo - Melim",
            "playlistId": 1
        },
        {
            "id": 3,
            "title": "CORES EM LIBRAS",
            "url": "https://www.youtube.com/embed/8CGSZs8eSNU",
            "description": "Todos os sinais - Para iniciantes",
            "playlistId": 1
        },
        {
            "id": 4,
            "title": "PARABÉNS PRA VOCÊ EM LIBRAS",
            "url": "https://www.youtube.com/embed/DU8UbudGqD0",
            "description": "Feliz aniversário em libras",
            "playlistId": 1
        },
        {
            "id": 5,
            "title": "APRENDA OS SINAIS DOS ANIMAIS",
            "url": "https://www.youtube.com/embed/Z08R9ZbRlrc",
            "description": "Neste vídeo, nós vamos ensinar vocês sinais de 10 animais.",
            "playlistId": 2
        },
        {
            "id": 6,
            "title": "ANIMAIS EM LIBRAS",
            "url": "https://www.youtube.com/embed/SR5ErJCyCmo",
            "description": "Ensinar o sinal de alguns animais em LIBRAS, de forma mais lúdica, pois ajuda na memorização e interpretação dos sinais.",
            "playlistId": 2
        },
        {
            "id": 7,
            "title": "ALFABETO EM LIBRAS",
            "url": "https://www.youtube.com/embed/ns-MylNcEic",
            "description": "Alfabeto em LIBRAS letra por letra com áudio",
            "playlistId": 2
        },
        {
            "id": 8,
            "title": "Aula 1",
            "url": "https://www.youtube.com/embed/dkEcOoUEonk",
            "description": "<b>Canal:</b> Inala Costa",
            "playlistId": 3
        },
        {
            "id": 9,
            "title": "Aula 2",
            "url": "https://www.youtube.com/embed/9AA5cn19lCQ",
            "description": "<b>Canal:</b> Inala Costa",
            "playlistId": 3
        },
        {
            "id": 10,
            "title": "Aula 3",
            "url": "https://www.youtube.com/embed/mVtffcc_KXs",
            "description": "<b>Canal:</b> Inala Costa",
            "playlistId": 3
        },
        {
            "id": 11,
            "title": "Você sabe o que é Libras?",
            "url": "https://www.youtube.com/embed/my5efyggee8",
            "description": "Libras é a sigla da Língua Brasileira de Sinais, uma língua de modalidade gestual-visual onde é possível se comunicar através de gestos, expressões faciais e corporais.",
            "playlistId": 4
        },
        {
            "id": 12,
            "title": "Você sabe a impotância da Libras?",
            "url": "https://www.youtube.com/embed/ilHLd3Eb-L0",
            "description": "Você vai perceber que tanto os surdos quanto as pessoas ao seu redor devem saber se comunicar através dessa língua, para que os surdos não se sintam excluídos e incompreendidos.",
            "playlistId": 4
        },
        {
            "id": 13,
            "title": "Regina Casé e Benedita",
            "url": "https://www.youtube.com/embed/3M36QIqR4_g",
            "description": "Regina Casé e sua filha Benedita, que é surda, explicam um pouco sobre a surdez, suas dificuldades e dão dicas de situações que os surdos passam.<br><a href='https://twitter.com/ReginaCase/status/1309881203911258112'>leia mais</a>",
            "playlistId": 0
        }
    ],
    "playlists": [
        {
            "id": 1,
            "name": "Aprenda Libras de forma divertida",
            "order": 1
        },
        {
            "id": 2,
            "name": "Aprendizado de Libras para crianças Ouvintes",
            "order": 2
        },
        {
            "id": 3,
            "name": "Curso Básico de Libras para Ouvintes",
            "order": 3
        },
        {
            "id": 4,
            "name": "Destaque",
            "order": 0
        }
    ],
    "news": [
        {
            "id": 1,
            "title": "Sign Aloud",
            "content": "Os estudantes Thomas Pryor y Navid Azodi da Universidade de Washington criaram umas luvas que podem traduzir a linguagem de sinais em texto ou voz. Isso facilitaria a comunicação entre pessoas que não conhecem a linguagem de sinais...",
            "date": "2020-10-01",
            "url": "https://www.linkedin.com/posts/wedercosta_signaloud-ugcPost-6712359811868045312-0IZT/",
            "imageUrl": "https://i.ytimg.com/vi/l01sdzJHCCM/maxresdefault.jpg"
        },
        {
            "id": 2,
            "title": "Regina Casé e Benedita",
            "content": "Regina Casé e sua filha Benedita, que é surda, explicam um pouco sobre a surdez, suas dificuldades e dão dicas de situações que os surdos passam.",
            "date": "2020-10-01",
            "url": "https://f5.folha.uol.com.br/celebridades/2020/09/no-dia-do-surdo-regina-case-fala-sobre-perda-de-audicao-da-filha-benedita.shtml",
            "imageUrl": "https://cdn-ofuxico.akamaized.net/img/upload/noticias/2019/08/20/regina-case-fala-sobre-a-surdez-da-filha-video_356509_36.jpg"
        },
        {
            "id": 3,
            "title": "Mascaras para surdos",
            "content": "Máscaras acentuam as dificuldades de comunicação de deficientes auditivos",
            "date": "2020-10-01",
            "url": "https://www.uol.com.br/vivabem/noticias/redacao/2020/09/26/mascaras-acentuam-as-dificuldades-de-comunicacao-de-deficientes-auditivos.html",
            "imageUrl": "https://conteudo.imguol.com.br/c/entretenimento/b1/2020/09/24/surdos-e-o-uso-de-mascara-1600968606430_v2_900x506.jpg"
        }
    ]
}
